{
  "/_global-error/page": "app/_global-error/page.js",
  "/_not-found/page": "app/_not-found/page.js",
  "/adding-post/page": "app/adding-post/page.js",
  "/api/auth/[...all]/route": "app/api/auth/[...all]/route.js",
  "/api/face/check-duplicate/route": "app/api/face/check-duplicate/route.js",
  "/api/face/verify-token/route": "app/api/face/verify-token/route.js",
  "/api/messages/[conversationId]/archive/route": "app/api/messages/[conversationId]/archive/route.js",
  "/api/messages/[conversationId]/route": "app/api/messages/[conversationId]/route.js",
  "/api/messages/route": "app/api/messages/route.js",
  "/api/messages/stream/[conversationId]/route": "app/api/messages/stream/[conversationId]/route.js",
  "/api/phone-otp/send/route": "app/api/phone-otp/send/route.js",
  "/api/phone-otp/verify/route": "app/api/phone-otp/verify/route.js",
  "/api/posts/[id]/comments/route": "app/api/posts/[id]/comments/route.js",
  "/api/posts/[id]/route": "app/api/posts/[id]/route.js",
  "/api/posts/[id]/save/route": "app/api/posts/[id]/save/route.js",
  "/api/posts/route": "app/api/posts/route.js",
  "/api/user/route": "app/api/user/route.js",
  "/icon.png/route": "app/icon.png/route.js",
  "/login/page": "app/login/page.js",
  "/messages/page": "app/messages/page.js",
  "/page": "app/page.js",
  "/post/[id]/page": "app/post/[id]/page.js",
  "/posts/page": "app/posts/page.js",
  "/profile/page": "app/profile/page.js",
  "/robots.txt/route": "app/robots.txt/route.js",
  "/settings/page": "app/settings/page.js",
  "/signup/page": "app/signup/page.js",
  "/sitemap.xml/route": "app/sitemap.xml/route.js",
  "/verify-mobile/page": "app/verify-mobile/page.js"
}